ParseXML.py
airflowconversion-1.0.2.dist-info/METADATA
airflowconversion-1.0.2.dist-info/WHEEL
airflowconversion-1.0.2.dist-info/top_level.txt
airflowconversion-1.0.2.dist-info/RECORD
