Metadata-Version: 2.1
Name: airflowconversion
Version: 1.0.2
Summary: Converting Oozie workflows in XML to Python (Airflow Syntax)
Home-page: https://repo1.uhc.com/artifactory/api/pypi/pypi-virtual/simple
Author: Rashi Agarwal
Author-email: rashi_agarwal@optum.com
